.gitignore
MANIFEST.in
PKG-INFO
README.txt
setup.cfg
setup.py
dist/medialog.summaryview-0.1.1.tar.gz
dist/medialog.summaryview-0.1.2.tar.gz
dist/medialog.summaryview-0.1.tar.gz
docs/HISTORY.txt
docs/INSTALL.txt
docs/LICENSE.GPL
docs/LICENSE.txt
medialog/.DS_Store
medialog/__init__.py
medialog.summaryview.egg-info/PKG-INFO
medialog.summaryview.egg-info/SOURCES.txt
medialog.summaryview.egg-info/dependency_links.txt
medialog.summaryview.egg-info/entry_points.txt
medialog.summaryview.egg-info/namespace_packages.txt
medialog.summaryview.egg-info/not-zip-safe
medialog.summaryview.egg-info/requires.txt
medialog.summaryview.egg-info/top_level.txt
medialog/summaryview/.DS_Store
medialog/summaryview/__init__.py
medialog/summaryview/configure.zcml
medialog/summaryview/interfaces.py
medialog/summaryview/profiles.zcml
medialog/summaryview/schemaextender.py
medialog/summaryview/browser/__init__.py
medialog/summaryview/browser/configure.zcml
medialog/summaryview/browser/folder_leadimage_view.pt
medialog/summaryview/browser/summary_view.pt
medialog/summaryview/locales/.DS_Store
medialog/summaryview/locales/medialog.summaryview.pot
medialog/summaryview/locales/plone.pot
medialog/summaryview/locales/en/.DS_Store
medialog/summaryview/locales/en/LC_MESSAGES/medialog.summaryview.po
medialog/summaryview/locales/en/LC_MESSAGES/plone.po
medialog/summaryview/locales/no/.DS_Store
medialog/summaryview/locales/no/LC_MESSAGES/medialog.summaryview.po
medialog/summaryview/locales/no/LC_MESSAGES/plone.po
medialog/summaryview/profiles/.DS_Store
medialog/summaryview/profiles/default/.DS_Store
medialog/summaryview/profiles/default/browserlayer.xml
medialog/summaryview/profiles/default/catalog.xml
medialog/summaryview/profiles/default/metadata.xml
medialog/summaryview/profiles/default/portal_atct.xml
medialog/summaryview/profiles/default/skins.xml
medialog/summaryview/profiles/default/skins/.DS_Store
medialog/summaryview/profiles/default/skins/medialog_summaryview/folder_summary_view.pt
medialog/summaryview/skins/.DS_Store
medialog/summaryview/skins/medialog_summaryview/folder_summary_view.pt
medialog/summaryview/tests/__init__.py
medialog/summaryview/tests/base.py
medialog/summaryview/tests/test_integration_unit.py