Metadata-Version: 1.0
Name: medialog.summaryview
Version: 0.1.3
Summary: Makes it possible to mark items so it does not show in summary view.
Home-page: https://github.com/collective/medialog.summaryview
Author: Grieg Medialog [Espen Moe-Nilssen]
Author-email: espen@medialog.no
License: GPL
Keywords: plone zope summaryview hide
Platform: UNKNOWN
Classifier: Framework :: Plone
Classifier: Programming Language :: Python
Classifier: Topic :: Software Development :: Libraries :: Python Modules
